codicefiscale/__init__.py
codicefiscale/codice_fiscale.py
codicefiscale/utils.py
codicefiscale/data/tabella_comuni.csv
codicefiscale/data/tabella_stati.csv
codicefiscale_ita-0.1.2.dist-info/LICENSE
codicefiscale_ita-0.1.2.dist-info/METADATA
codicefiscale_ita-0.1.2.dist-info/WHEEL
codicefiscale_ita-0.1.2.dist-info/top_level.txt
codicefiscale_ita-0.1.2.dist-info/RECORD
