Metadata-Version: 2.1
Name: codicefiscale-ita
Version: 0.1.2
Summary: Libreria per generare e validare codici fiscali italiani
Home-page: https://github.com/FilippoCasadei/py-codicefiscale-lib.git
Author: Filippo Casadei
Author-email: filippo.casadei2004@gmail.com
Classifier: Programming Language :: Python :: 3
Classifier: License :: OSI Approved :: MIT License
Classifier: Operating System :: OS Independent
Requires-Python: >=3.7
License-File: LICENSE
